LICENSE
MANIFEST.in
setup.cfg
setup.py
wsgibrotli/__init__.py
wsgibrotli/br.py
wsgibrotli.egg-info/PKG-INFO
wsgibrotli.egg-info/SOURCES.txt
wsgibrotli.egg-info/dependency_links.txt
wsgibrotli.egg-info/requires.txt
wsgibrotli.egg-info/top_level.txt