Metadata-Version: 1.1
Name: wsgibrotli
Version: 0.0.4
Summary: Brotli compression WSGI middleware
Home-page: https://github.com/vaygr/wsgibrotli
Author: Vlad Glagolev
Author-email: stealth@sourcemage.org
License: MIT
Platform: UNKNOWN
Classifier: Programming Language :: Python :: 2
Classifier: Programming Language :: Python :: 3
Classifier: License :: OSI Approved :: MIT License
Classifier: Operating System :: OS Independent
